{"Louisiana Board Of Regents": "1201 N 3rd St #6, Baton Rouge, LA 70802", "Emporia State University": "1 Kellogg Cir, Emporia, KS 66801", "Morehead State University": "150 University Blvd, Morehead, KY 40351", "State University Of Ny Potsdam": "44 Pierrepont Ave, Potsdam, NY 13676", "St. Mary'S College Of Maryland": "47645 College Dr, St Marys City, MD 20686", "Clark County Education Association": "4230 McLeod Dr, Las Vegas, NV 89121", "Bureau Of Indian Affairs": "1849 C Street, N.W Washington, D.C. 20240", "College Of William And Mary": "200 Stadium Dr, Williamsburg, VA 23185", "Georgia College And State University": "231 W Hancock St, Milledgeville, GA 31061", "Illinois College": "1101 W College Ave, Jacksonville, IL 62650", "University Of Kentucky": "129 Taylor Education Bldg, Lexington, KY 40506", "Shorter University": "315 Shorter Ave, Rome, GA 30165", "Winthrop University": "701 Oakland Ave, Rock Hill, SC 29730", "St. Bonaventure University-School Of Education": "3261 W State St, St Bonaventure, NY 14778", "Augusta University": "1120 15th St, Augusta, GA 30912", "California University Of Pennsylvania": "250 University Ave, California, PA 15419", "Murrieta Valley Usd": "41870 Mcalby Ct, Murrieta, CA 92562", "Northampton City Public Schools": "7207 Young Street, Machipongo, VA 23405", "Pierce College": "6201 Winnetka Ave, Woodland Hills, CA 91371", "Southern Connecticut State University": "501 Crescent St, New Haven, CT 06515", "Rowan University": "201 Mullica Hill Rd, Glassboro, NJ 08028", "Illinois State University Board Of Trustees": "2020 Illinois State University, Normal, IL USA", "Teach For America-Kansas City": "2000 Baltimore Ave Ste 300, Kansas City, MO 64108", "Armstrong State University": "11935 Abercorn St, Savannah, GA 31419", "University Of Detroit Mercy Lib": "4001 W McNichols Rd, Detroit, MI 48221", "University Of Alabama Birmingham": "901 13th St S, Birmingham, AL 35294", "Tuscaloosa City Schools": "1210 21st Avenue, Tuscaloosa, AL 35401", "Greenville College": "315 E College Ave, Greenville, IL 62246", "University Of The Cumberland": "6178 College Station Drive, Williamsburg, KY 40769", "New York University": "New York, NY 10003", "Farleigh Dickinson University": "1000 River Rd, Teaneck, NJ 07666", "University Of Nc Greensboro": "1400 Spring Garden St, Greensboro, NC 27412", "Christina School District": "50 Gender Road, Newark, DE 19713", "Miami University-Oxford": "501 E High St, Oxford, OH 45056", "Orange County Department Of Education": "200 Kalmus Dr, Costa Mesa, CA 92626", "Piedmont College": "1021 Central Ave, Demorest, GA 30535", "Fayetteville State University": "1200 Murchison Rd, Fayetteville, NC 28301", "Kennesaw State University": "1000 Chastain Rd NW, Kennesaw, GA 30144", "Fort Mill School District": "2233 Deerfield Dr, Fort Mill, SC 29715", "Saint Andrew'S School": "3900 Jog Road, Boca Raton, FL 33434", "Western Governors University": "4001 S 700 E #300, Salt Lake City, UT 84107", "California State University": "444 North Capitol St NW # 207, Washington, DC 20001", "Hawaii State Teachers Association": "1200 Ala Kapuna St, Honolulu, HI 96819", "Billings Senior High School": "425 Grand Ave, Billings, MT 59101", "Portland State University": "1825 SW Broadway, Portland, OR 97201", "University Of Mississippi": "850 Insight Park Avenue, University ,MS 38677", "Mississippi State University": "75 B. S. Hood Road, Mississippi State, MS 39762", "East Stroudsburg University & Colonial Iu": "6 Dansford Drive Colonial IU 20 Easton, PA 18045", "University Of Missouri-Kansas City": "5000 Holmes St, Kansas City, MO 64110", "St. Thomas Aquinas College": "125 NY-340, Sparkill, NY 10976", "Mississippi Dept Of Education": "359 N West St, Jackson, MS 39201", "Lamar Cisd": "3911 AVE I, ROSENBERG, 77471-3901", "University Of Virginia": "1001 N EMMET ST  Charlottesville, VA 22904-4202 ", "University Of Pacific": "3601 Pacific Avenue, Stockton, CA 95211", "South Australia Doe": "31 Flinders Street, Adelaide SA 5000", "Delta State University": "1003 W Sunflower Rd, Cleveland, MS 38733", "Walla Walla Public Schools": "364 S Park Street, Walla Walla,WA 99362", "Durham Public Schools": "511 Cleveland Street Durham, NC 27701-3334", "University Of Nc Charlotte": "9201 University City Blvd, Charlotte, NC 28223", "Dickinson State University": "294 Campus Drive, Dickinson, ND 58601", "Central Connecticut State University": "1615 Stanley St, New Britain, CT 06050", "University Of Holy Cross (La)": "4123 Woodland Drive, New Orleans, LA 70131", "Northwestern State University": "350 Sam Sibley Road, Natchitoches, LA 71497", "East Tennessee State University": "Box 70684, Johnson City, TN 37614", "Region  Education Service Ctr": "7145 West Tidwell Rd, Houston TX 77092-2096", "Georgia Gwinnett College": "1000 University Center Ln, Lawrenceville, GA 30043", "El Rancho Unified School District": "9333 Loch Lomond Drive, Pico Rivera CA 90660", "Louisiana State University Shreveport": "One University Pl, Shreveport, LA 71115", "Kansas State University": "261 Bluemont Hall, Manhattan, KS 66506", "Lake Havasu Usd": "2200 Havasupai Blvd, Lake Havasu City, AZ 86403", "Middle Tennessee State University": "Box 14,1301 E. Main Street, Murfreesboro, TN 37129", "John P. Ellbogen Foundation": "P.O. Box 1670, Laramie, KY 82073", "Pinecrest Academy Of Nevada": "225 Cadence Drive, Henderson, NV 89015", "Campbell University": "143 Main St, Buies Creek, NC 27506", "Unc Wilmington": "601 S College Rd, Wilmington, NC 28403", "University Of Southern Mississippi": "118 College Dr, Hattiesburg, MS 39406", "Kentucky Epsb": "300 Sower Blvd, Frankfort, KY 40601", "University Of Louisiana At Monroe": NaN, "Arlington Public Schools": "2110 Washington Blvd, Arlington, VA 22204", "Alcorn State University": "1000 Asu Dr, Lorman, MS 39096", "Austin Peay State University": "601 College St, Clarksville, TN 37044", "Alabama A&M University-College Of Education": "4900 Meridian St N, Huntsville, AL 35811", "Albertus Magnus College": "700 Prospect St, New Haven, CT 06511", "Birmingham-Southern College": "900 Arkadelphia Road, Birmingham, AL  35254", "American University": "4400 Massachusetts Ave NW, Washington, DC 20016", "Cerra": "525 Eden Terrace, Rock Hill, SC 29730", "Albuquerque Public Schools": "Po Box 25704 Albuquerque, NM 87125", "Georgia College & State University": "Box 070 College of Education Milledgeville, GA 31061", "American College Of Education": "101 W Ohio St Suite 1200, Indianapolis, IN 46204", "Charleston Southern University": "9200 University Blvd, North Charleston, SC 29406", "Bainbridge Island School District": "8489 Madison Ave NE Bainbridge Island, WA", "Brenau University": "500 Washington St SE, Gainesville, GA 30501", "Central Washington University": "400 E University Way, Ellensburg, WA 98926", "Bloomboard, Inc.": "135 University Avenue, Suite 200\nPalto Alto, CA 94301", "Bowling Green Independent Schools": "1211 Center Street, Bowling Green, KY  42101", "Catawba College": "2300 W Innes St, Salisbury, NC 28144", "Chapman University": "1 University Dr, Orange, CA 92866", "City University Of New York": "425 E 25th St, New York, NY 10010", "Auburn University": "5042 Haley Center, Auburn, AL 36849", "Bellarmine University": "2001 Newburg RD, Louisville, KY 40205", "Brigham Young University \u2013 Hawaii": "220 Kulanui St, Laie, HI 96762", "California State Polytechnic University Pomona-Education/Ceis": "3801 W. Temple Ave., Bldg. 6 Room 220, Pomona, CA 91768", "Belhaven University": "1500 Peachtree Street, Jackson, MS  39202", "Ca State University, Stanislaus": "1 University Cir, Turlock, CA 95382", "Brock University": "1812 Sir Isaac Brock Way, St. Catharines, Ontario, Canada L2S3A1", "Ca State University Chico": "400 W 1st St, Chico, CA 95929", "Chicago State University": "9501 S. King Dr., Chicago, IL  60628                   ", "Clayton State University": "2000 Clayton State Blvd, Morrow, GA 30260", "Appalachian State University": "287 Rivers St, Boone, NC 28608", "Berea College": "Knapp Hall 104B, CPO 2195, Berea, KY  40404", "California State University Long Beach": "1250 Bellflower Blvd, Long Beach, CA 90840", "Bridgewater College": "402 E. College St., Bridgewater, VA  22812", "Arcadia University": "450 S. Easton Road,, Glenside, PA  19038", "California State University, Fullerton": "800 N State College Blvd, Fullerton, CA 92831", "Bard College": "30 Campus Rd, Annandale-On-Hudson, NY 12504", "Berry College": "2377 Martha Berry Highway NW, Mount Berry, GA  30149", "Bradley University": "1501 W Bradley Ave, Peoria, IL 61625", "Anderson University": "316 Boulevard, Anderson, SC 29621", "Barton College": "400 Atlantic Christian e West NE, Wilson, NC 27893", "Brandeis University": "415 South St, Waltham, MA 02453", "California State University Northridge": "18111 Nordhoff St, Northridge, CA 91330", "Clarion University Of Pennsylvania": "840 Wood St, Clarion, PA 16214", "Calvert County Public Schools": "1305 Dares Beach Rd, Prince Frederick, MD 20678", "Alverno College": "3400 S 43rd St, Milwaukee, WI 53234", "Aquinas College": "4210 Harding Pike, Nashville, TN 37205", "Bowling Green State University": "101 Education Bldg., BGSU, Bowling Green, OH  43403", "Ball State University": "2000 W University Ave, Muncie, IN 47306", "Ca State University Dominguez Hills": "1000 E Victoria St, Carson, CA 90747", "Alderson Broaddus University": "101 College Hill Rd, Philippi, WV 26416", "Capital University": "E Main St & College Ave, Bexley, OH 43209", "Brown University": "10 Prospect St., Box A, Providence, RI  02912", "Arkansas Northeastern College": "2501 S Division St, Blytheville, AR 72315"}